playstation_store_scraper/__init__.py
playstation_store_scraper/scraper.py
playstation_store_scraper-1.0.0.dist-info/METADATA
playstation_store_scraper-1.0.0.dist-info/WHEEL
playstation_store_scraper-1.0.0.dist-info/licenses/LICENSE
playstation_store_scraper-1.0.0.dist-info/RECORD
