Metadata-Version: 2.4
Name: playstation_store_scraper
Version: 1.0.0
Summary: A web scraper for the PlayStation Store that retrieves and lists all available games with details such as title, price, platform, and more.
License: MIT
License-File: LICENSE
Author: Hadi Mohseni
Author-email: hadimohseni1996@gmail.com
Requires-Python: >=3.12,<4.0
Classifier: License :: OSI Approved :: MIT License
Classifier: Programming Language :: Python :: 3
Classifier: Programming Language :: Python :: 3.12
Classifier: Programming Language :: Python :: 3.13
Classifier: Programming Language :: Python :: 3.14
Requires-Dist: beautifulsoup4 (>=4.14.2,<5.0.0)
